aigc/__init__.py
aigc/aigc.py
aigc/clis/__init__.py
aigc/clis/cli.py
aigc-2023.2.15.14.18.59.dist-info/AUTHORS.rst
aigc-2023.2.15.14.18.59.dist-info/LICENSE
aigc-2023.2.15.14.18.59.dist-info/METADATA
aigc-2023.2.15.14.18.59.dist-info/WHEEL
aigc-2023.2.15.14.18.59.dist-info/entry_points.txt
aigc-2023.2.15.14.18.59.dist-info/top_level.txt
aigc-2023.2.15.14.18.59.dist-info/RECORD
