Metadata-Version: 2.1
Name: aigc
Version: 2023.2.15.14.18.59
Summary: AI生成
Home-page: https://github.com/yuanjie-ai/aigc
Author: aigc
Author-email: 313303303@qq.com
License: MIT license
Keywords: aigc
Platform: UNKNOWN
Classifier: Development Status :: 2 - Pre-Alpha
Classifier: Intended Audience :: Developers
Classifier: License :: OSI Approved :: MIT License
Classifier: Natural Language :: English
Classifier: Programming Language :: Python :: 3
Classifier: Programming Language :: Python :: 3.6
Classifier: Programming Language :: Python :: 3.7
Classifier: Programming Language :: Python :: 3.8
Requires-Python: >=3.6
License-File: LICENSE
License-File: AUTHORS.rst
Requires-Dist: meutils
